rouver/__init__.py
rouver/args.py
rouver/exceptions.py
rouver/handler.py
rouver/html.py
rouver/py.typed
rouver/response.py
rouver/router.py
rouver/status.py
rouver/test.py
rouver/types.py
rouver/util.py
rouver_test/__init__.py
rouver_test/args.py
rouver_test/exceptions.py
rouver_test/handler.py
rouver_test/html.py
rouver_test/response.py
rouver_test/router.py
rouver_test/status.py
rouver_test/test.py
rouver_test/testutil.py
rouver_test/util.py
rouver-2.7.0.dist-info/METADATA
rouver-2.7.0.dist-info/WHEEL
rouver-2.7.0.dist-info/licenses/LICENSE
rouver-2.7.0.dist-info/RECORD
