Metadata-Version: 2.4
Name: rouver
Version: 2.7.0
Summary: A microframework
License: MIT
License-File: LICENSE
Author: Sebastian Rittau
Author-email: srittau@rittau.biz
Requires-Python: >=3.10
Classifier: Development Status :: 5 - Production/Stable
Classifier: Topic :: Internet :: WWW/HTTP :: WSGI
Requires-Dist: dectest (>=1.0.0,<2)
Requires-Dist: werkzeug (>=2.0,<4)
Project-URL: Bug Tracker, https://github.com/srittau/rouver/issues
Project-URL: Changes, https://github.com/srittau/rouver/blob/main/CHANGELOG.md
Project-URL: GitHub, https://github.com/srittau/rouver
Project-URL: Homepage, https://github.com/srittau/rouver
Project-URL: Repository, https://github.com/srittau/rouver
